skilleter_readable/__init__.py
skilleter_readable/readable.py
skilleter_readable/test.py
skilleter_readable-0.0.8.dist-info/licenses/LICENSE
skilleter_readable-0.0.8.dist-info/METADATA
skilleter_readable-0.0.8.dist-info/WHEEL
skilleter_readable-0.0.8.dist-info/entry_points.txt
skilleter_readable-0.0.8.dist-info/top_level.txt
skilleter_readable-0.0.8.dist-info/RECORD
