Metadata-Version: 2.4
Name: skilleter-readable
Version: 0.0.8
Summary: A utility for making log files (particularly Terraform logs) more readable and comparable
Author-email: John Skilleter <john@skilleter.org.uk>
Project-URL: Home, https://skilleter.org.uk
Project-URL: Repository, https://gitlab.com/skilleter/skilleter-readable
Project-URL: Issues, https://gitlab.com/skilleter/skilleter-readable/-/issues
Classifier: Programming Language :: Python :: 3
Classifier: License :: OSI Approved :: GNU General Public License v3 or later (GPLv3+)
Classifier: Operating System :: OS Independent
Requires-Python: >=3.9
License-File: LICENSE
Requires-Dist: skilleter-modules
Dynamic: license-file
